Metadata-Version: 2.1
Name: ppco
Version: 0.1.0
Summary: ...
Author: wauo
Author-email: markadc@126.com
Requires-Python: >=3.10
